pyrattler_recipe_autogen/__init__.py
pyrattler_recipe_autogen/_version.py
pyrattler_recipe_autogen/cli.py
pyrattler_recipe_autogen/core.py
pyrattler_recipe_autogen/demo.py
pyrattler_recipe_autogen-0.20.0.dist-info/METADATA
pyrattler_recipe_autogen-0.20.0.dist-info/WHEEL
pyrattler_recipe_autogen-0.20.0.dist-info/entry_points.txt
pyrattler_recipe_autogen-0.20.0.dist-info/licenses/LICENSE
pyrattler_recipe_autogen-0.20.0.dist-info/RECORD
