Metadata-Version: 2.4
Name: pyrattler-recipe-autogen
Version: 0.20.0
Summary: Generate Rattler-Build recipe.yaml from pyproject.toml
Project-URL: homepage, https://github.com/millsks/pyrattler-recipe-autogen
Project-URL: repository, https://github.com/millsks/pyrattler-recipe-autogen.git
Project-URL: documentation, https://github.com/millsks/pyrattler-recipe-autogen.git#README
Project-URL: issues, https://github.com/millsks/pyrattler-recipe-autogen/issues
Author: millsks
License: MIT License
License-File: LICENSE
Classifier: Development Status :: 3 - Alpha
Classifier: Intended Audience :: Developers
Classifier: License :: OSI Approved :: MIT License
Classifier: Programming Language :: Python :: 3
Classifier: Programming Language :: Python :: 3.9
Classifier: Programming Language :: Python :: 3.10
Classifier: Programming Language :: Python :: 3.11
Classifier: Programming Language :: Python :: 3.12
Classifier: Programming Language :: Python :: 3.13
Classifier: Topic :: Software Development :: Build Tools
Classifier: Topic :: System :: Software Distribution
Requires-Python: >=3.9
Requires-Dist: pyyaml
Requires-Dist: toml
Requires-Dist: tomli; python_version < '3.11'
Requires-Dist: types-pyyaml
Requires-Dist: types-toml
